hammerdraw_setup_manager.py
hammerdraw_setup_manager-0.1.1.dist-info/LICENSE
hammerdraw_setup_manager-0.1.1.dist-info/METADATA
hammerdraw_setup_manager-0.1.1.dist-info/WHEEL
hammerdraw_setup_manager-0.1.1.dist-info/top_level.txt
hammerdraw_setup_manager-0.1.1.dist-info/RECORD
